{
  "project_info": {
    "project_number": "657148841423",
    "project_id": "symvolta",
    "storage_bucket": "symvolta.firebasestorage.app"
  },
  "client": [
    {
      "client_info": {
        "mobilesdk_app_id": "1:657148841423:android:34c2889a7bca6a97dd56ba",
        "android_client_info": {
          "package_name": "com.symvolta.game"
        }
      },
      "oauth_client": [],
      "api_key": [
        {
          "current_key": "AIzaSyBd_uCKHYp-7IiY1Cl-xqj5povGXDH8YXI"
        }
      ],
      "services": {
        "appinvite_service": {
          "other_platform_oauth_client": []
        }
      }
    }
  ],
  "configuration_version": "1"
}